MANIFEST.in
README.md
README.rst
mp3hash.py
setup.py
mp3hash.egg-info/PKG-INFO
mp3hash.egg-info/SOURCES.txt
mp3hash.egg-info/dependency_links.txt
mp3hash.egg-info/top_level.txt
scripts/mp3hash
tests/__init__.py
tests/integration/__init__.py
tests/integration/test_cli.py
tests/integration/test_hash.py
tests/unit/__init__.py
tests/unit/test_id3v1.py
tests/unit/test_id3v1_extended.py
tests/unit/test_id3v2.py
tests/unit/test_parse_7bitint.py