Metadata-Version: 1.1
Name: mp3hash
Version: 0.1
Summary: Music file hasher
Home-page: http://github.com/jvrsantacruz/mp3hash
Author: Javier Santacruz
Author-email: javier.santacruz.lc@gmail.com
License: UNKNOWN
Platform: Any
Classifier: Development Status :: 3 - Alpha
Classifier: License :: OSI Approved :: GNU General Public License v3 (GPLv3)
Classifier: Programming Language :: Python
Classifier: Programming Language :: Python :: 2
Classifier: Programming Language :: Python :: 2.7
